LICENSE
README.md
setup.cfg
setup.py
thehsi/__init__.py
thehsi/callers.py
thehsi/kernel.py
thehsi.egg-info/PKG-INFO
thehsi.egg-info/SOURCES.txt
thehsi.egg-info/dependency_links.txt
thehsi.egg-info/requires.txt
thehsi.egg-info/top_level.txt